[{"x": 10, "y": 2}, {"x": 11, "y": 2}, {"x": 16, "y": 2}, {"x": 17, "y": 2}, {"x": 25, "y": 2}, {"x": 26, "y": 2}, {"x": 10, "y": 3}, {"x": 12, "y": 3}, {"x": 15, "y": 3}, {"x": 17, "y": 3}, {"x": 25, "y": 3}, {"x": 26, "y": 3}, {"x": 12, "y": 4}, {"x": 15, "y": 4}, {"x": 11, "y": 5}, {"x": 16, "y": 5}, {"x": 11, "y": 6}, {"x": 12, "y": 6}, {"x": 15, "y": 6}, {"x": 16, "y": 6}, {"x": 13, "y": 7}, {"x": 14, "y": 7}, {"x": 37, "y": 9}, {"x": 38, "y": 9}, {"x": 1, "y": 10}, {"x": 2, "y": 10}, {"x": 27, "y": 10}, {"x": 34, "y": 10}, {"x": 35, "y": 10}, {"x": 38, "y": 10}, {"x": 1, "y": 11}, {"x": 4, "y": 11}, {"x": 5, "y": 11}, {"x": 25, "y": 11}, {"x": 26, "y": 11}, {"x": 28, "y": 11}, {"x": 34, "y": 11}, {"x": 36, "y": 11}, {"x": 37, "y": 11}, {"x": 2, "y": 12}, {"x": 3, "y": 12}, {"x": 5, "y": 12}, {"x": 25, "y": 12}, {"x": 28, "y": 12}, {"x": 33, "y": 12}, {"x": 6, "y": 13}, {"x": 12, "y": 13}, {"x": 13, "y": 13}, {"x": 14, "y": 13}, {"x": 25, "y": 13}, {"x": 26, "y": 13}, {"x": 27, "y": 13}, {"x": 33, "y": 13}, {"x": 6, "y": 14}, {"x": 11, "y": 14}, {"x": 14, "y": 14}, {"x": 34, "y": 14}, {"x": 36, "y": 14}, {"x": 37, "y": 14}, {"x": 2, "y": 15}, {"x": 3, "y": 15}, {"x": 5, "y": 15}, {"x": 11, "y": 15}, {"x": 13, "y": 15}, {"x": 14, "y": 15}, {"x": 34, "y": 15}, {"x": 35, "y": 15}, {"x": 38, "y": 15}, {"x": 1, "y": 16}, {"x": 4, "y": 16}, {"x": 5, "y": 16}, {"x": 12, "y": 16}, {"x": 37, "y": 16}, {"x": 38, "y": 16}, {"x": 1, "y": 17}, {"x": 2, "y": 17}, {"x": 25, "y": 19}, {"x": 26, "y": 19}, {"x": 23, "y": 20}, {"x": 24, "y": 20}, {"x": 27, "y": 20}, {"x": 28, "y": 20}, {"x": 23, "y": 21}, {"x": 28, "y": 21}, {"x": 24, "y": 22}, {"x": 27, "y": 22}, {"x": 13, "y": 23}, {"x": 14, "y": 23}, {"x": 22, "y": 23}, {"x": 24, "y": 23}, {"x": 27, "y": 23}, {"x": 29, "y": 23}, {"x": 13, "y": 24}, {"x": 14, "y": 24}, {"x": 22, "y": 24}, {"x": 23, "y": 24}, {"x": 28, "y": 24}, {"x": 29, "y": 24}]